markdown_lists/__init__.py
markdown_lists-2019.3.30.dist-info/METADATA
markdown_lists-2019.3.30.dist-info/WHEEL
markdown_lists-2019.3.30.dist-info/top_level.txt
markdown_lists-2019.3.30.dist-info/RECORD
